py_dbms_cli-3.1.3113.dist-info/licenses/LICENSE
pydbms/__init__.py
pydbms/db/db_base.py
pydbms/db/db_manager.py
pydbms/db/mysql.py
pydbms/export/export_base.py
pydbms/export/export_csv.py
pydbms/export/export_json.py
pydbms/export/export_manager.py
pydbms/main/__init__.py
pydbms/main/config.py
pydbms/main/core.py
pydbms/main/dependencies.py
pydbms/main/meta_handler.py
pydbms/main/profile.py
pydbms/main/pydbms_mysql.py
pydbms/main/pydbms_path.py
pydbms/main/query_parse_and_classify.py
pydbms/main/runtime.py
py_dbms_cli-3.1.3113.dist-info/METADATA
py_dbms_cli-3.1.3113.dist-info/WHEEL
py_dbms_cli-3.1.3113.dist-info/entry_points.txt
py_dbms_cli-3.1.3113.dist-info/top_level.txt
py_dbms_cli-3.1.3113.dist-info/RECORD
