Metadata-Version: 2.4
Name: py-dbms-cli
Version: 3.1.3113
Summary: A modern, secure, aesthetic and your ultimate DBMS client. Implemented as a CLI (Command-Line Interface) tool and written 100% in Python
Author-email: Anish Sethi <sethi.dynasty123@gmail.com>
License: Copyright 2025 Anish Sethi
Project-URL: Homepage, https://github.com/Anish-Sethi-12122/py-dbms-cli
Project-URL: Source, https://github.com/Anish-Sethi-12122/py-dbms-cli
Project-URL: Issues, https://github.com/Anish-Sethi-12122/py-dbms-cli/issues
Requires-Python: >=3.10
License-File: LICENSE
Requires-Dist: mysql-connector-python
Requires-Dist: rich
Requires-Dist: pyfiglet
Requires-Dist: sqlparse
Requires-Dist: pwinput
Dynamic: license-file
